chenx_utils/__init__.py
chenx_utils/http_requests.py
chenx_utils/model.py
chenx_utils/redis.py
chenx_utils/upload.py
chenx_utils/upload_sync.py
chenx_utils/util.py
chenx_utils/data/config.py
chenx_utils/data/response_json.py
chenx_utils-0.1.3.2.dist-info/METADATA
chenx_utils-0.1.3.2.dist-info/WHEEL
chenx_utils-0.1.3.2.dist-info/licenses/LICENSE
chenx_utils-0.1.3.2.dist-info/RECORD
