Metadata-Version: 2.3
Name: chenx_utils
Version: 0.1.3.2
Summary: chenx_utils is a package for eos to yidongyun 
Project-URL: Homepage, https://github.com/cdmstrong
Author-email: Daniel Chen <cdmstrong123@gmail.com>
Classifier: License :: OSI Approved :: MIT License
Classifier: Operating System :: OS Independent
Classifier: Programming Language :: Python :: 3
Requires-Python: >=3.9
Requires-Dist: aiohttp
Requires-Dist: boto3==1.35.92
Requires-Dist: pydantic
Requires-Dist: pydantic-core
Requires-Dist: pyrender
Requires-Dist: redis
Requires-Dist: requests
